qudi/runnable.py
qudi/artwork/icons/accessories-calculator.svg
qudi/artwork/icons/application-exit.svg
qudi/artwork/icons/auto_pois.svg
qudi/artwork/icons/camera-photo.svg
qudi/artwork/icons/configure.svg
qudi/artwork/icons/correct-tilt.svg
qudi/artwork/icons/correct-tilt_off.svg
qudi/artwork/icons/correct-tilt_toggle.svg
qudi/artwork/icons/correct-tilt_toggle_off.svg
qudi/artwork/icons/dialog-warning.svgz
qudi/artwork/icons/document-new.svg
qudi/artwork/icons/document-open.svgz
qudi/artwork/icons/document-save.svg
qudi/artwork/icons/edit-clear.svgz
qudi/artwork/icons/edit-copy.svgz
qudi/artwork/icons/edit-cut.svgz
qudi/artwork/icons/edit-delete-shred.svgz
qudi/artwork/icons/edit-delete.svgz
qudi/artwork/icons/go-home.svg
qudi/artwork/icons/go-next.svgz
qudi/artwork/icons/go-previous.svgz
qudi/artwork/icons/goto-poi.svgz
qudi/artwork/icons/list-add.svg
qudi/artwork/icons/list-remove.svg
qudi/artwork/icons/media-playback-pause.svgz
qudi/artwork/icons/media-playback-start.svgz
qudi/artwork/icons/media-playback-stop.svgz
qudi/artwork/icons/media-record.svgz
qudi/artwork/icons/mouse_pointer.svg
qudi/artwork/icons/network-connect.svg
qudi/artwork/icons/network-disconnect.svg
qudi/artwork/icons/new_poi_crosshair.svg
qudi/artwork/icons/new_poi_mouse.svg
qudi/artwork/icons/object-rotate-left.svgz
qudi/artwork/icons/object-rotate-right.svgz
qudi/artwork/icons/optimize-position-poi.svgz
qudi/artwork/icons/optimize-position.svg
qudi/artwork/icons/periodic-refind-poi.svgz
qudi/artwork/icons/poi-new.svg
qudi/artwork/icons/record-counter.svgz
qudi/artwork/icons/restart-counter.svg
qudi/artwork/icons/scan-depth-loop.svg
qudi/artwork/icons/scan-depth-restart.svg
qudi/artwork/icons/scan-depth-start.svg
qudi/artwork/icons/scan-stop.svg
qudi/artwork/icons/scan-xy-loop.svg
qudi/artwork/icons/scan-xy-restart.svg
qudi/artwork/icons/scan-xy-start.svg
qudi/artwork/icons/start-counter.svg
qudi/artwork/icons/stop-counter.svg
qudi/artwork/icons/utilities-terminal.svgz
qudi_core-1.6.0.dist-info/AUTHORS.md
qudi_core-1.6.0.dist-info/LICENSE
qudi_core-1.6.0.dist-info/LICENSE.LESSER
qudi_core-1.6.0.dist-info/METADATA
qudi_core-1.6.0.dist-info/WHEEL
qudi_core-1.6.0.dist-info/entry_points.txt
qudi_core-1.6.0.dist-info/top_level.txt
qudi_core-1.6.0.dist-info/RECORD
