Metadata-Version: 2.2
Name: qudi-core
Version: 1.6.0
Summary: A modular measurement application framework
Project-URL: Homepage, https://github.com/Ulm-IQO/qudi-core
Project-URL: Documentation, https://ulm-iqo.github.io/qudi-core/
Project-URL: Repository, https://github.com/Ulm-IQO/qudi-core.git
Project-URL: Bug Tracker, https://github.com/Ulm-IQO/qudi-core/issues
Project-URL: Changelog, https://github.com/Ulm-IQO/qudi-core/blob/main/docs/changelog.md
Keywords: qudi,diamond,quantum,confocal,automation,experiment,measurement,framework,lab,laboratory,instrumentation,instrument,modular
Classifier: Development Status :: 5 - Production/Stable
Classifier: Environment :: Win32 (MS Windows)
Classifier: Environment :: X11 Applications
Classifier: Environment :: MacOS X
Classifier: Intended Audience :: Developers
Classifier: Intended Audience :: Science/Research
Classifier: Intended Audience :: End Users/Desktop
Classifier: License :: OSI Approved :: GNU Lesser General Public License v3 (LGPLv3)
Classifier: Natural Language :: English
Classifier: Operating System :: Microsoft :: Windows :: Windows 8
Classifier: Operating System :: Microsoft :: Windows :: Windows 8.1
Classifier: Operating System :: Microsoft :: Windows :: Windows 10
Classifier: Operating System :: Microsoft :: Windows :: Windows 11
Classifier: Operating System :: MacOS :: MacOS X
Classifier: Operating System :: Unix
Classifier: Operating System :: POSIX :: Linux
Classifier: Programming Language :: Python :: 3.8
Classifier: Programming Language :: Python :: 3.9
Classifier: Programming Language :: Python :: 3.10
Classifier: Topic :: Scientific/Engineering
Classifier: Topic :: Software Development :: Libraries :: Application Frameworks
Classifier: Topic :: Software Development :: User Interfaces
Requires-Python: <3.11,>=3.8
License-File: LICENSE
License-File: LICENSE.LESSER
License-File: AUTHORS.md
Requires-Dist: cycler>=0.10.0
Requires-Dist: entrypoints>=0.3
Requires-Dist: fysom>=2.1.6
Requires-Dist: GitPython>=3.1.24
Requires-Dist: jupyter>=1.0.0
Requires-Dist: jupytext>=1.13.0
Requires-Dist: lmfit>=1.0.3
Requires-Dist: matplotlib>=3.4.3
Requires-Dist: numpy<2,>=1.21.3
Requires-Dist: pyqtgraph>=0.13.0
Requires-Dist: PySide2==5.15.2.1
Requires-Dist: rpyc<6,>=5.0.1
Requires-Dist: ruamel.yaml>=0.17.16
Requires-Dist: scipy>=1.7.1
Requires-Dist: jsonschema>=4.2.1
Requires-Dist: qtconsole>=5.5.0
